corgibrowser/__init__.py
corgibrowser/corgi_cloud_integration/__init__.py
corgibrowser/corgi_cloud_integration/azure_direct_operations.py
corgibrowser/corgi_cloud_integration/cloud_integration.py
corgibrowser/corgi_cloud_integration/queues_schemas/__init__.py
corgibrowser/corgi_cloud_integration/queues_schemas/corgi_web_queue_version_1.py
corgibrowser/corgi_cloud_integration/tables/__init__.py
corgibrowser/corgi_cloud_integration/tables/corgi_hash_table.py
corgibrowser/corgi_cloud_integration/tables/corgi_web_entity.py
corgibrowser/corgi_cloud_integration/tables/corgi_web_request_log.py
corgibrowser/corgi_cloud_integration/tables/corgi_web_scrape_log.py
corgibrowser/corgi_cloud_integration/tables/corgi_web_trottling.py
corgibrowser/corgi_cloud_integration/tables/corgiweb_queuepreference.py
corgibrowser/corgi_cloud_integration/tables/corgiweb_storage_analytics.py
corgibrowser/corgi_crawler/RobotsCache.py
corgibrowser/corgi_crawler/__init__.py
corgibrowser/corgi_crawler/crawler.py
corgibrowser/corgi_crawler/crawler_processor.py
corgibrowser/corgi_crawler/visited_url_processor.py
corgibrowser/corgi_data_analytics_and_ai/__init__.py
corgibrowser/corgi_data_analytics_and_ai/data_analytics_and_ai.py
corgibrowser/corgi_datasets/DataSetsManager.py
corgibrowser/corgi_datasets/__init__.py
corgibrowser/corgi_datasets/newspapers/__init__.py
corgibrowser/corgi_datasets/newspapers/usa/__init__.py
corgibrowser/corgi_datasets/newspapers/usa/arizona.py
corgibrowser/corgi_datasets/newspapers/usa/arkansas.py
corgibrowser/corgi_datasets/newspapers/usa/california.py
corgibrowser/corgi_datasets/newspapers/usa/colorado.py
corgibrowser/corgi_datasets/newspapers/usa/connecticut.py
corgibrowser/corgi_datasets/newspapers/usa/delaware.py
corgibrowser/corgi_datasets/newspapers/usa/extra.py
corgibrowser/corgi_datasets/newspapers/usa/georgia.py
corgibrowser/corgi_datasets/newspapers/usa/hawaii.py
corgibrowser/corgi_datasets/newspapers/usa/illinois.py
corgibrowser-0.1.0.dist-info/LICENSE
corgibrowser-0.1.0.dist-info/METADATA
corgibrowser-0.1.0.dist-info/WHEEL
corgibrowser-0.1.0.dist-info/top_level.txt
corgibrowser-0.1.0.dist-info/RECORD
