Metadata-Version: 2.1
Name: corgibrowser
Version: 0.1.0
Summary: Corgi Browser
Home-page: https://github.com/j-enriquez/corgibrowser
Author: Jose Enriquez
Author-email: joseaenriqueza@hotmail.com
Project-URL: Documentation, https://corgibrowser.readthedocs.io/en/latest/
Classifier: Programming Language :: Python :: 3
Classifier: License :: OSI Approved :: MIT License
Classifier: Operating System :: OS Independent
License-File: LICENSE
Requires-Dist: adal ==1.2.7
Requires-Dist: azure-applicationinsights ==0.1.1
Requires-Dist: azure-batch ==4.1.3
Requires-Dist: azure-common ==1.1.28
Requires-Dist: azure-core ==1.30.0
Requires-Dist: azure-cosmosdb-nspkg ==2.0.2
Requires-Dist: azure-cosmosdb-table ==1.0.6
Requires-Dist: azure-data-tables ==12.5.0
Requires-Dist: azure-datalake-store ==0.0.53
Requires-Dist: azure-eventgrid ==1.3.0
Requires-Dist: azure-graphrbac ==0.40.0
Requires-Dist: azure-identity ==1.15.0
Requires-Dist: azure-keyvault ==1.1.0
Requires-Dist: azure-loganalytics ==0.1.1
Requires-Dist: azure-mgmt ==4.0.0
Requires-Dist: azure-mgmt-advisor ==1.0.1
Requires-Dist: azure-mgmt-applicationinsights ==0.1.1
Requires-Dist: azure-mgmt-authorization ==0.50.0
Requires-Dist: azure-mgmt-batch ==5.0.1
Requires-Dist: azure-mgmt-batchai ==2.0.0
Requires-Dist: azure-mgmt-billing ==0.2.0
Requires-Dist: azure-mgmt-cdn ==3.1.0
Requires-Dist: azure-mgmt-cognitiveservices ==3.0.0
Requires-Dist: azure-mgmt-commerce ==1.0.1
Requires-Dist: azure-mgmt-compute ==4.6.2
Requires-Dist: azure-mgmt-consumption ==2.0.0
Requires-Dist: azure-mgmt-containerinstance ==1.5.0
Requires-Dist: azure-mgmt-containerregistry ==2.8.0
Requires-Dist: azure-mgmt-containerservice ==4.4.0
Requires-Dist: azure-mgmt-cosmosdb ==0.4.1
Requires-Dist: azure-mgmt-datafactory ==0.6.0
Requires-Dist: azure-mgmt-datalake-analytics ==0.6.0
Requires-Dist: azure-mgmt-datalake-nspkg ==3.0.1
Requires-Dist: azure-mgmt-datalake-store ==0.5.0
Requires-Dist: azure-mgmt-datamigration ==1.0.0
Requires-Dist: azure-mgmt-devspaces ==0.1.0
Requires-Dist: azure-mgmt-devtestlabs ==2.2.0
Requires-Dist: azure-mgmt-dns ==2.1.0
Requires-Dist: azure-mgmt-eventgrid ==1.0.0
Requires-Dist: azure-mgmt-eventhub ==2.6.0
Requires-Dist: azure-mgmt-hanaonazure ==0.1.1
Requires-Dist: azure-mgmt-iotcentral ==0.1.0
Requires-Dist: azure-mgmt-iothub ==0.5.0
Requires-Dist: azure-mgmt-iothubprovisioningservices ==0.2.0
Requires-Dist: azure-mgmt-keyvault ==1.1.0
Requires-Dist: azure-mgmt-loganalytics ==0.2.0
Requires-Dist: azure-mgmt-logic ==3.0.0
Requires-Dist: azure-mgmt-machinelearningcompute ==0.4.1
Requires-Dist: azure-mgmt-managementgroups ==0.1.0
Requires-Dist: azure-mgmt-managementpartner ==0.1.1
Requires-Dist: azure-mgmt-maps ==0.1.0
Requires-Dist: azure-mgmt-marketplaceordering ==0.1.0
Requires-Dist: azure-mgmt-media ==1.0.1
Requires-Dist: azure-mgmt-monitor ==0.5.2
Requires-Dist: azure-mgmt-msi ==0.2.0
Requires-Dist: azure-mgmt-network ==2.7.0
Requires-Dist: azure-mgmt-notificationhubs ==2.1.0
Requires-Dist: azure-mgmt-nspkg ==3.0.2
Requires-Dist: azure-mgmt-policyinsights ==0.1.0
Requires-Dist: azure-mgmt-powerbiembedded ==2.0.0
Requires-Dist: azure-mgmt-rdbms ==1.9.0
Requires-Dist: azure-mgmt-recoveryservices ==0.3.0
Requires-Dist: azure-mgmt-recoveryservicesbackup ==0.3.0
Requires-Dist: azure-mgmt-redis ==5.0.0
Requires-Dist: azure-mgmt-relay ==0.1.0
Requires-Dist: azure-mgmt-reservations ==0.2.1
Requires-Dist: azure-mgmt-resource ==2.2.0
Requires-Dist: azure-mgmt-scheduler ==2.0.0
Requires-Dist: azure-mgmt-search ==2.1.0
Requires-Dist: azure-mgmt-servicebus ==0.5.3
Requires-Dist: azure-mgmt-servicefabric ==0.2.0
Requires-Dist: azure-mgmt-signalr ==0.1.1
Requires-Dist: azure-mgmt-sql ==0.9.1
Requires-Dist: azure-mgmt-storage ==2.0.0
Requires-Dist: azure-mgmt-subscription ==0.2.0
Requires-Dist: azure-mgmt-trafficmanager ==0.50.0
Requires-Dist: azure-mgmt-web ==0.35.0
Requires-Dist: azure-nspkg ==3.0.2
Requires-Dist: azure-servicebus ==0.21.1
Requires-Dist: azure-servicefabric ==6.3.0.0
Requires-Dist: azure-servicemanagement-legacy ==0.20.7
Requires-Dist: azure-storage-blob ==12.19.0
Requires-Dist: azure-storage-common ==1.4.2
Requires-Dist: azure-storage-file ==1.4.0
Requires-Dist: azure-storage-nspkg ==3.1.0
Requires-Dist: azure-storage-queue ==12.9.0
Requires-Dist: beautifulsoup4 ==4.12.3
Requires-Dist: certifi ==2024.2.2
Requires-Dist: cffi ==1.16.0
Requires-Dist: charset-normalizer ==3.3.2
Requires-Dist: cryptography ==42.0.2
Requires-Dist: idna ==3.6
Requires-Dist: isodate ==0.6.1
Requires-Dist: msal ==1.26.0
Requires-Dist: msal-extensions ==1.1.0
Requires-Dist: msrest ==0.7.1
Requires-Dist: msrestazure ==0.6.4
Requires-Dist: multidict ==6.0.5
Requires-Dist: oauthlib ==3.2.2
Requires-Dist: packaging ==23.2
Requires-Dist: portalocker ==2.8.2
Requires-Dist: pycparser ==2.21
Requires-Dist: PyJWT ==2.8.0
Requires-Dist: python-dateutil ==2.8.2
Requires-Dist: requests ==2.31.0
Requires-Dist: requests-oauthlib ==1.3.1
Requires-Dist: six ==1.16.0
Requires-Dist: soupsieve ==2.5
Requires-Dist: typing-extensions ==4.9.0
Requires-Dist: urllib3 ==2.2.0
Requires-Dist: yarl ==1.9.4
Requires-Dist: openai ~=1.12.0
Requires-Dist: python-dotenv
Requires-Dist: parsel
Requires-Dist: aiohttp
Requires-Dist: asyncio
